overhang_surrogates.py
overhang_surrogates-1.0.dist-info/LICENSE
overhang_surrogates-1.0.dist-info/WHEEL
overhang_surrogates-1.0.dist-info/METADATA
overhang_surrogates-1.0.dist-info/RECORD
